{
  "$schema": "https://schema.management.azure.com/schemas/2019-04-01/deploymentTemplate.json#",
  "contentVersion": "1.0.0.0",
  "metadata": {
    "_generator": {
      "name": "bicep",
      "version": "0.37.4.10188",
      "templateHash": "1816115362252355908"
    }
  },
  "parameters": {
    "location": {
      "type": "string",
      "defaultValue": "westus",
      "metadata": {
        "description": "Location for the Content Understanding service"
      }
    },
    "serviceName": {
      "type": "string",
      "defaultValue": "[format('content-understanding-{0}', uniqueString(resourceGroup().id))]",
      "metadata": {
        "description": "Name for the Content Understanding service"
      }
    },
    "storageAccountName": {
      "type": "string",
      "defaultValue": "[format('storage{0}', uniqueString(resourceGroup().id))]",
      "metadata": {
        "description": "Name for the storage account"
      }
    }
  },
  "resources": [
    {
      "type": "Microsoft.Storage/storageAccounts",
      "apiVersion": "2023-05-01",
      "name": "[parameters('storageAccountName')]",
      "location": "[parameters('location')]",
      "kind": "StorageV2",
      "sku": {
        "name": "Standard_LRS"
      },
      "properties": {
        "accessTier": "Hot",
        "allowBlobPublicAccess": false,
        "allowSharedKeyAccess": true,
        "supportsHttpsTrafficOnly": true,
        "minimumTlsVersion": "TLS1_2",
        "encryption": {
          "services": {
            "blob": {
              "enabled": true
            },
            "file": {
              "enabled": true
            }
          },
          "keySource": "Microsoft.Storage"
        },
        "networkAcls": {
          "defaultAction": "Allow"
        }
      }
    },
    {
      "type": "Microsoft.CognitiveServices/accounts",
      "apiVersion": "2024-10-01",
      "name": "[parameters('serviceName')]",
      "location": "[parameters('location')]",
      "kind": "AIServices",
      "sku": {
        "name": "S0"
      },
      "properties": {
        "customSubDomainName": "[parameters('serviceName')]",
        "publicNetworkAccess": "Enabled"
      }
    }
  ],
  "outputs": {
    "endpoint": {
      "type": "string",
      "value": "[reference(resourceId('Microsoft.CognitiveServices/accounts', parameters('serviceName')), '2024-10-01').endpoint]"
    },
    "resourceId": {
      "type": "string",
      "value": "[resourceId('Microsoft.CognitiveServices/accounts', parameters('serviceName'))]"
    },
    "name": {
      "type": "string",
      "value": "[parameters('serviceName')]"
    },
    "storageAccountName": {
      "type": "string",
      "value": "[parameters('storageAccountName')]"
    },
    "storageAccountId": {
      "type": "string",
      "value": "[resourceId('Microsoft.Storage/storageAccounts', parameters('storageAccountName'))]"
    },
    "storageAccountPrimaryEndpoints": {
      "type": "object",
      "value": "[reference(resourceId('Microsoft.Storage/storageAccounts', parameters('storageAccountName')), '2023-05-01').primaryEndpoints]"
    }
  }
}